ros_unique_identifier_msgs-2.7.0.data/data/include/unique_identifier_msgs/unique_identifier_msgs/msg/rosidl_generator_c__visibility_control.h
ros_unique_identifier_msgs-2.7.0.data/data/include/unique_identifier_msgs/unique_identifier_msgs/msg/rosidl_generator_cpp__visibility_control.hpp
ros_unique_identifier_msgs-2.7.0.data/data/include/unique_identifier_msgs/unique_identifier_msgs/msg/rosidl_typesupport_fastrtps_c__visibility_control.h
ros_unique_identifier_msgs-2.7.0.data/data/include/unique_identifier_msgs/unique_identifier_msgs/msg/rosidl_typesupport_fastrtps_cpp__visibility_control.h
ros_unique_identifier_msgs-2.7.0.data/data/include/unique_identifier_msgs/unique_identifier_msgs/msg/rosidl_typesupport_introspection_c__visibility_control.h
ros_unique_identifier_msgs-2.7.0.data/data/include/unique_identifier_msgs/unique_identifier_msgs/msg/uuid.h
ros_unique_identifier_msgs-2.7.0.data/data/include/unique_identifier_msgs/unique_identifier_msgs/msg/uuid.hpp
ros_unique_identifier_msgs-2.7.0.data/data/include/unique_identifier_msgs/unique_identifier_msgs/msg/detail/uuid__builder.hpp
ros_unique_identifier_msgs-2.7.0.data/data/include/unique_identifier_msgs/unique_identifier_msgs/msg/detail/uuid__description.c
ros_unique_identifier_msgs-2.7.0.data/data/include/unique_identifier_msgs/unique_identifier_msgs/msg/detail/uuid__functions.c
ros_unique_identifier_msgs-2.7.0.data/data/include/unique_identifier_msgs/unique_identifier_msgs/msg/detail/uuid__functions.h
ros_unique_identifier_msgs-2.7.0.data/data/include/unique_identifier_msgs/unique_identifier_msgs/msg/detail/uuid__rosidl_typesupport_fastrtps_c.h
ros_unique_identifier_msgs-2.7.0.data/data/include/unique_identifier_msgs/unique_identifier_msgs/msg/detail/uuid__rosidl_typesupport_fastrtps_cpp.hpp
ros_unique_identifier_msgs-2.7.0.data/data/include/unique_identifier_msgs/unique_identifier_msgs/msg/detail/uuid__rosidl_typesupport_introspection_c.h
ros_unique_identifier_msgs-2.7.0.data/data/lib/python3.10/site-packages/unique_identifier_msgs-2.7.0-py3.10.egg-info/PKG-INFO
ros_unique_identifier_msgs-2.7.0.data/data/lib/python3.10/site-packages/unique_identifier_msgs-2.7.0-py3.10.egg-info/SOURCES.txt
ros_unique_identifier_msgs-2.7.0.data/data/lib/python3.10/site-packages/unique_identifier_msgs-2.7.0-py3.10.egg-info/dependency_links.txt
ros_unique_identifier_msgs-2.7.0.data/data/lib/python3.10/site-packages/unique_identifier_msgs-2.7.0-py3.10.egg-info/top_level.txt
ros_unique_identifier_msgs-2.7.0.dist-info/METADATA
ros_unique_identifier_msgs-2.7.0.dist-info/WHEEL
ros_unique_identifier_msgs-2.7.0.dist-info/top_level.txt
ros_unique_identifier_msgs-2.7.0.dist-info/RECORD
ros_unique_identifier_msgs-2.7.0.dist-info/licenses/LICENSE
