Metadata-Version: 2.4
Name: ros-unique-identifier-msgs
Version: 2.7.0
Summary: ROS 2 package providing standard messages for Universally Unique Identifiers (UUIDs).
License-File: LICENSE
Requires-Dist: ros-rosidl-core-runtime~=0.3.1
Dynamic: description
Dynamic: description-content-type
Dynamic: license-file
Dynamic: requires-dist
Dynamic: summary
